AUTHORS.rst
CONTRIBUTING.rst
HISTORY.rst
LICENSE
MANIFEST.in
README.rst
setup.cfg
setup.py
docs/Makefile
docs/authors.rst
docs/conf.py
docs/contributing.rst
docs/history.rst
docs/index.rst
docs/installation.rst
docs/make.bat
docs/readme.rst
docs/usage.rst
gls_unibox_api/__init__.py
gls_unibox_api/api.py
gls_unibox_api/fields.py
gls_unibox_api/tags.py
gls_unibox_api.egg-info/PKG-INFO
gls_unibox_api.egg-info/SOURCES.txt
gls_unibox_api.egg-info/dependency_links.txt
gls_unibox_api.egg-info/not-zip-safe
gls_unibox_api.egg-info/top_level.txt
tests/__init__.py
tests/example_response.txt
tests/test_gls_unibox_api.py