Metadata-Version: 1.1
Name: gls-unibox-api
Version: 0.0.1.1
Summary: Python API for GLS Unibox Logistics System
Home-page: https://github.com/openlabs/gls_unibox_api
Author: Sharoon Thomas
Author-email: info@openlabs.co.in
License: BSD
Keywords: gls_unibox_api
Platform: UNKNOWN
Classifier: Development Status :: 2 - Pre-Alpha
Classifier: Intended Audience :: Developers
Classifier: License :: OSI Approved :: BSD License
Classifier: Natural Language :: English
Classifier: Programming Language :: Python :: 2
Classifier: Programming Language :: Python :: 2.6
Classifier: Programming Language :: Python :: 2.7
Classifier: Programming Language :: Python :: 3
Classifier: Programming Language :: Python :: 3.3
Classifier: Programming Language :: Python :: 3.4
